Package/__init__.py
reconocimiento-1.1.1.dist-info/LICENSE.txt
reconocimiento-1.1.1.dist-info/METADATA
reconocimiento-1.1.1.dist-info/WHEEL
reconocimiento-1.1.1.dist-info/top_level.txt
reconocimiento-1.1.1.dist-info/RECORD
