Metadata-Version: 2.1
Name: reconocimiento
Version: 1.1.1
Summary: Este paquete nos permite reconocer y registrar           placas
Home-page: UNKNOWN
Author: Sebastian Zambrano
Author-email: Sebastianrza@gmail.com
License: UNKNOWN
Platform: UNKNOWN
